PYWDEIMS101/WenDi_WDDBA101.py
PYWDEIMS101/WenDi_WDEIMS101.py
PYWDEIMS101/WenDi_WDSM101.py
PYWDEIMS101/__init__.py
PYWDEIMS101-1.0.1.dist-info/LICENSE
PYWDEIMS101-1.0.1.dist-info/METADATA
PYWDEIMS101-1.0.1.dist-info/WHEEL
PYWDEIMS101-1.0.1.dist-info/top_level.txt
PYWDEIMS101-1.0.1.dist-info/RECORD
