Metadata-Version: 2.1
Name: PYWDEIMS101
Version: 1.0.1
Summary: WDEIMS组件
Home-page: https://git.dev.tencent.com/Tom_Chenyong/WDEIMS101.git
Author: Tom Chen
Author-email: tom.chenyong@qq.com
License: UNKNOWN
Platform: UNKNOWN
Classifier: Programming Language :: Python :: 3
Classifier: License :: OSI Approved :: MIT License
Classifier: Operating System :: OS Independent
